xt_cvdata/__init__.py
xt_cvdata/apis/__init__.py
xt_cvdata/apis/builder.py
xt_cvdata/apis/coco.py
xt_cvdata/apis/image_folder.py
xt_cvdata/apis/open_images.py
xt_cvdata/apis/vott_csv.py
xt_cvdata/apis/yolo.py
xt_cvdata/datasets/__init__.py
xt_cvdata/datasets/datasets.py
xt_cvdata/datasets/nyu_depth.py
xt_cvdata/datasets/voc.py
xt_cvdata/transforms/__init__.py
xt_cvdata/transforms/transforms.py
xt_cvdata-0.8.0.dist-info/METADATA
xt_cvdata-0.8.0.dist-info/WHEEL
xt_cvdata-0.8.0.dist-info/top_level.txt
xt_cvdata-0.8.0.dist-info/RECORD
