Metadata-Version: 2.1
Name: xt-cvdata
Version: 0.8.0
Summary: Utilities for building and working with computer vision datasets
Home-page: https://github.com/XtractTech/xt-cvdata
Author: Xtract AI
Author-email: info@xtract.ai
License: UNKNOWN
Platform: UNKNOWN
Classifier: Programming Language :: Python :: 3
Classifier: Operating System :: OS Independent
Provides: xt_cvdata
Requires-Dist: numpy
Requires-Dist: pandas
Requires-Dist: torch
Requires-Dist: torchvision
Requires-Dist: h5py
Requires-Dist: pillow
Requires-Dist: matplotlib
Requires-Dist: tqdm
Requires-Dist: pycocotools
Requires-Dist: albumentations
